Metadata-Version: 2.1
Name: mySQL-Co
Version: 0.1.2
Summary: This is mysql saver , partition , set primary key and update with dataframe
Author: Kasra-Khaksar
Author-email: ksra13khaksar@gmail.com
Requires-Python: >=3.6
